net_contextdiff/__init__.py
net_contextdiff/__main__.py
net_contextdiff/config.py
net_contextdiff/diff.py
net_contextdiff/misc.py
net_contextdiff/ios/__init__.py
net_contextdiff/ios/config.py
net_contextdiff/ios/diff.py
net_contextdiff/ios/utils.py
net_contextdiff/ios/commands/__init__.py
net_contextdiff/ios/commands/interface.py
net_contextdiff/ios/commands/lists.py
net_contextdiff/ios/commands/other.py
net_contextdiff/ios/commands/router.py
net_contextdiff/ios/converters/__init__.py
net_contextdiff/ios/converters/interface.py
net_contextdiff/ios/converters/lists.py
net_contextdiff/ios/converters/other.py
net_contextdiff/ios/converters/router.py
net_contextdiff-0.15.12.dist-info/LICENSE
net_contextdiff-0.15.12.dist-info/METADATA
net_contextdiff-0.15.12.dist-info/WHEEL
net_contextdiff-0.15.12.dist-info/top_level.txt
net_contextdiff-0.15.12.dist-info/RECORD
