Metadata-Version: 2.1
Name: net-contextdiff
Version: 0.15.12
Summary: Compare network device configuration files using contextual structures
Home-page: https://gitlab.developers.cam.ac.uk/uis/netsys/udn/net-contextdiff
Author: Robert Franklin
Author-email: rcf34@cam.ac.uk
Classifier: Programming Language :: Python :: 3
Classifier: License :: OSI Approved :: MIT License
Classifier: Operating System :: OS Independent
License-File: LICENSE
Requires-Dist: deepops (>=1.7.1)
Requires-Dist: netaddr
